bntransformer/__init__.py
bntransformer/pipeline.py
bntransformer/tokenizer.py
bntransformer/utils.py
bntransformer-2.1.0.dist-info/LICENSE
bntransformer-2.1.0.dist-info/METADATA
bntransformer-2.1.0.dist-info/WHEEL
bntransformer-2.1.0.dist-info/top_level.txt
bntransformer-2.1.0.dist-info/RECORD
