Metadata-Version: 2.1
Name: bntransformer
Version: 2.1.0
Summary: bengali transformer bengali language processing state of the art transformer
Home-page: https://github.com/sagorbrur/bntransformer
Author: Sagor Sarker
Author-email: sagorhem3532@gmail.com
License: MIT
Platform: UNKNOWN
Classifier: Programming Language :: Python :: 3
Classifier: License :: OSI Approved :: MIT License
Classifier: Operating System :: OS Independent
Requires-Python: >=3.6
Requires-Dist: transformers (==4.6.1)
Requires-Dist: sentencepiece
